po2dataset/__init__.py
po2dataset/po2dataset.py
po2dataset-0.5.1.dist-info/LICENSE
po2dataset-0.5.1.dist-info/METADATA
po2dataset-0.5.1.dist-info/WHEEL
po2dataset-0.5.1.dist-info/entry_points.txt
po2dataset-0.5.1.dist-info/top_level.txt
po2dataset-0.5.1.dist-info/RECORD
