Metadata-Version: 2.1
Name: po2dataset
Version: 0.5.1
Summary: Python tool to extract sentences from po files and create language datasets for machine translation
Author-email: Urtzi Odriozola <urtzi.odriozola@gmail.com>
License: MIT License
Project-URL: Homepage, https://github.com/urtzai/po2dataset
Project-URL: Documentation, https://github.com/urtzai/po2dataset/blob/main/README.md
Project-URL: Repository, https://github.com/urtzai/po2dataset
Project-URL: Bug Tracker, https://github.com/urtzai/po2dataset/issues
Project-URL: Changelog, https://github.com/urtzai/po2dataset/blob/main/CHANGELOG.md
Keywords: po,dataset,NLP,argostranslate,libretranslate,language,translation
Classifier: Development Status :: 4 - Beta
Classifier: Intended Audience :: Developers
Classifier: Topic :: Software Development :: Build Tools
Classifier: License :: OSI Approved :: MIT License
Classifier: Programming Language :: Python :: 3
Classifier: Programming Language :: Python :: 3.9
Classifier: Programming Language :: Python :: 3.10
Classifier: Programming Language :: Python :: 3.11
Classifier: Programming Language :: Python :: 3.12
Classifier: Programming Language :: Python :: 3.13
License-File: LICENSE
Requires-Dist: polib ==1.2.0
Requires-Dist: argparse ==1.4.0
Requires-Dist: tox ==4.23.2
Requires-Dist: requests ==2.32.3
